{
    "title": "公共服务组文档库",
    "language" : "zh-hans",
    "ignores": ["_book","node_modules"], 
    "plugins": [
        "-lunr",
        "-search",
        "search-pro",
        "chapter-fold",
        "expandable-chapters",
        "back-to-top-button",
        "splitter",
        "page-toc-button",
        "back-to-top-button",
        "-highlight",
        "prism",
        "code",
        "hide-element",
        "-sharing",
        "sharing-plus"
    ],
    "pluginsConfig": {
        "prism": {
            "css": [
                "prismjs/themes/prism-funky.css"
            ]
        },
        "sharing": {
            "douban": true,
            "qq": true,
            "qzone": true,
            "weibo": true,
            "all": [
                "douban",
                "weibo",
                "qq",
                "qzone"
            ]
        },
        "hide-element": {
            "elements": [
                ".gitbook-link"
            ]
        },
        "page-toc-button": {
            "maxTocDepth": 2,
            "minTocSize": 2
        }
    }
}